aittps/__init__.py
aittps/aittps.py
tests/__init__.py
tests/test_encryption.py
aittps-1.1.0.dist-info/LICENSE
aittps-1.1.0.dist-info/METADATA
aittps-1.1.0.dist-info/WHEEL
aittps-1.1.0.dist-info/top_level.txt
aittps-1.1.0.dist-info/RECORD
