Metadata-Version: 2.1
Name: aittps
Version: 1.1.0
Summary: AITTPS SDK: Autonomous HTTPS for AI Agents
Home-page: https://github.com/yourusername/aittps
Author: Your Name
Author-email: your.email@example.com
Classifier: Programming Language :: Python :: 3
Classifier: License :: OSI Approved :: MIT License
Classifier: Operating System :: OS Independent
Requires-Python: >=3.8
License-File: LICENSE
Requires-Dist: cryptography>=41.0.0
